django_light_auth/__init__.py
django_light_auth/admin.py
django_light_auth/apps.py
django_light_auth/runtimes.py
django_light_auth/tests.py
django_light_auth/views.py
django_light_auth-0.2.3.dist-info/licenses/LICENSE
django_light_auth-0.2.3.dist-info/METADATA
django_light_auth-0.2.3.dist-info/WHEEL
django_light_auth-0.2.3.dist-info/top_level.txt
django_light_auth-0.2.3.dist-info/RECORD
