Metadata-Version: 2.4
Name: django-light-auth
Version: 0.2.3
Summary: Django Lightweight Authentication without models and databases, only depend on the signed cookies and the Django's SessionMiddleware.
Author: Rex Zhang
Author-email: rex.zhang@gmail.com
Project-URL: homepage, https://github.com/rexzhang/django-light-auth
Keywords: django,auth
Classifier: Development Status :: 4 - Beta
Classifier: Framework :: Django :: 5.0
Requires-Python: >=3.10
License-File: LICENSE
Requires-Dist: django>=5.0
Dynamic: license-file
